MANIFEST.in
README.md
applypvs
dbdlint
getpvs
setup.cfg
setup.py
epics_pypdb.egg-info/PKG-INFO
epics_pypdb.egg-info/SOURCES.txt
epics_pypdb.egg-info/dependency_links.txt
epics_pypdb.egg-info/requires.txt
epics_pypdb.egg-info/top_level.txt
pyPDB/__init__.py
pyPDB/dbdlint.py
pyPDB/getdbd.py
pyPDB/getedl.py
pyPDB/getopi.py
pyPDB/dbd/__init__.py
pyPDB/dbd/ast.py
pyPDB/dbd/expand.py
pyPDB/dbd/lex.py
pyPDB/dbd/show.py
pyPDB/dbd/yacc.py
pyPDB/dbd/test/__init__.py
pyPDB/dbd/test/test_parser.py
pyPDB/po/__init__.py
pyPDB/test/__init__.py
pyPDB/test/test_lint.py