Metadata-Version: 1.0
Name: epics-pypdb
Version: 0.1
Summary: Utilities for working with EPICS PDB files
Home-page: UNKNOWN
Author: Michael Davidsaver
Author-email: mdavidsaver@gmail.com
License: UNKNOWN
Platform: UNKNOWN
